multiSyncPy/__init__.py
multiSyncPy/data_generation.py
multiSyncPy/synchrony_metrics.py
multiSyncPy/visualisations.py
multiSyncPy-0.1.2.dist-info/LICENSE.txt
multiSyncPy-0.1.2.dist-info/METADATA
multiSyncPy-0.1.2.dist-info/WHEEL
multiSyncPy-0.1.2.dist-info/top_level.txt
multiSyncPy-0.1.2.dist-info/RECORD
