Metadata-Version: 2.1
Name: multiSyncPy
Version: 0.1.2
Summary: Functions to quantify multivariate synchrony
Home-page: https://github.com/cslab-hub/multiSyncPy
Author: Dan Hudson
Author-email: daniel.dominic.hudson@uni-osnabrueck.de
License: GNU LGPL
Classifier: License :: OSI Approved :: GNU Library or Lesser General Public License (LGPL)
Classifier: Programming Language :: Python :: 3
Classifier: Programming Language :: Python :: 3.7
License-File: LICENSE.txt
Requires-Dist: numpy
Requires-Dist: scipy
Requires-Dist: scikit-learn
Requires-Dist: seaborn
Requires-Dist: matplotlib
